ohirstar_scaleheight_lifetime/ohirstar_scaleheight_lifetime.py
ohirstar_scaleheight_lifetime-1.0.0.dist-info/LICENSE
ohirstar_scaleheight_lifetime-1.0.0.dist-info/METADATA
ohirstar_scaleheight_lifetime-1.0.0.dist-info/WHEEL
ohirstar_scaleheight_lifetime-1.0.0.dist-info/top_level.txt
ohirstar_scaleheight_lifetime-1.0.0.dist-info/RECORD
