Metadata-Version: 2.1
Name: ohirstar-scaleheight-lifetime
Version: 1.0.0
Summary: Estimate a distribution and lifetime of star in the Galaxy.
Home-page: https://github.com/yuriuno/ohirstar_scaleheight_lifetime
Author: yuriuno
Author-email: k8688309@kadai.jp
License: MIT
Keywords: scaleheight scale-height lifetime OH/IR star
Platform: UNKNOWN
Classifier: License :: OSI Approved :: MIT License
Classifier: Programming Language :: Python :: 3.7
Requires-Dist: numpy
Requires-Dist: scipy
